spiralweb/__init__.py
spiralweb/__main__.py
spiralweb/api.py
spiralweb/model.py
spiralweb/parser.py
spiralweb/parsetab.py
spiralweb-0.3.dist-info/DESCRIPTION.rst
spiralweb-0.3.dist-info/METADATA
spiralweb-0.3.dist-info/RECORD
spiralweb-0.3.dist-info/WHEEL
spiralweb-0.3.dist-info/entry_points.txt
spiralweb-0.3.dist-info/metadata.json
spiralweb-0.3.dist-info/top_level.txt
