Metadata-Version: 2.0
Name: spiralweb
Version: 0.3
Summary: A lightweight-markup based literate programming system
Home-page: https://github.com/michaeljmcd/spiralweb
Author: Michael McDermott
Author-email: mmcdermott@mad-computer-scientist.com
License: MIT
Keywords: literate programming,lp,markdown
Platform: UNKNOWN
Requires-Dist: ply
